.DS_Store
TeaML/TeaML.py
TeaML/__init__.py
TeaML/conf.ini
TeaML/examples.csv
TeaML/examples.py
TeaML/version.py
TeaML/experiment/VariableCluster.py
TeaML/experiment/__init__.py
TeaML/utils/__init__.py
TeaML/utils/auto_bin_woe.py
TeaML/utils/tea_encoder.py
TeaML/utils/tea_filter.py
TeaML/utils/tea_utils.py
TeaML-0.2.0.dist-info/LICENSE
TeaML-0.2.0.dist-info/METADATA
TeaML-0.2.0.dist-info/WHEEL
TeaML-0.2.0.dist-info/top_level.txt
TeaML-0.2.0.dist-info/RECORD
