Metadata-Version: 2.1
Name: TeaML
Version: 0.2.0
Summary: Automated Modeling in Financial Domain. TeaML is a simple and design friendly automatic modeling learning framework.
Home-page: https://github.com/TianjinMouth/TeaML
Author: DiegoSong, TianjinMouth
Author-email: ssyshenn@gmail.com, tjszgaosan@sina.cn
License: Apache License 2.0
Platform: UNKNOWN
Classifier: License :: OSI Approved :: Apache Software License
Classifier: Programming Language :: Python :: 3.6
Classifier: Programming Language :: Python :: Implementation :: CPython
Classifier: Programming Language :: Python :: Implementation :: PyPy
Requires-Python: >3.6
Requires-Dist: pandas (==0.24.2)
Requires-Dist: numpy (==1.16.3)
Requires-Dist: openpyxl (==2.6.2)
Requires-Dist: setuptools (==41.0.1)
Requires-Dist: scipy (==1.2.1)
Requires-Dist: statsmodels (==0.9.0)
Requires-Dist: tqdm (==4.34.0)
Requires-Dist: shap (==0.28.5)
Requires-Dist: scikit-learn (==0.20.2)
